pymusicplayer/__init__.py
pymusicplayer/music_player.py
pymusicplayer/song.py
PyMusicPlayer-1.0.0.dist-info/LICENSE
PyMusicPlayer-1.0.0.dist-info/METADATA
PyMusicPlayer-1.0.0.dist-info/WHEEL
PyMusicPlayer-1.0.0.dist-info/top_level.txt
PyMusicPlayer-1.0.0.dist-info/RECORD
