Metadata-Version: 2.1
Name: PyMusicPlayer
Version: 1.0.0
Summary: An MP3 music player interface
Home-page: https://github.com/cmdvmd/pymusicplayer
Author: cmdvmd
License: UNKNOWN
Platform: UNKNOWN
Classifier: Programming Language :: Python
Classifier: Programming Language :: Python :: 3
Classifier: License :: OSI Approved :: MIT License
Classifier: Topic :: Multimedia :: Sound/Audio
Classifier: Topic :: Multimedia :: Sound/Audio :: Players
Classifier: Topic :: Software Development :: Libraries :: pygame
